spoke_web/__init__.py
spoke_web/cli.py
spoke_web/conn.py
pyspoke_web-0.1.2.dist-info/LICENSE
pyspoke_web-0.1.2.dist-info/METADATA
pyspoke_web-0.1.2.dist-info/WHEEL
pyspoke_web-0.1.2.dist-info/entry_points.txt
pyspoke_web-0.1.2.dist-info/top_level.txt
pyspoke_web-0.1.2.dist-info/RECORD
