Metadata-Version: 2.1
Name: pyspoke-web
Version: 0.1.2
Summary: websocket extensions for pyspoke
Home-page: https://gitlab.com/samflam/pyspoke-web
Author-email: pyspoke-web@samflam.com
License: UNKNOWN
Platform: UNKNOWN
Classifier: Programming Language :: Python :: 3
Classifier: License :: OSI Approved :: MIT License
Classifier: Operating System :: POSIX :: Linux
Requires-Python: >=3.7
License-File: LICENSE
Requires-Dist: websockets (>=10)
Requires-Dist: pyspoke (>=1.1)
